business_rules/__init__.py
business_rules/__version__.py
business_rules/actions.py
business_rules/engine.py
business_rules/fields.py
business_rules/operators.py
business_rules/utils.py
business_rules/variables.py
test/__init__.py
test/test_actions_class.py
test/test_engine_logic.py
test/test_integration.py
test/test_operators.py
test/test_operators_class.py
test/test_variables.py
test/test_variables_class.py
business_rules_reloaded-2.0.1.dist-info/LICENSE
business_rules_reloaded-2.0.1.dist-info/METADATA
business_rules_reloaded-2.0.1.dist-info/WHEEL
business_rules_reloaded-2.0.1.dist-info/top_level.txt
business_rules_reloaded-2.0.1.dist-info/RECORD
