Metadata-Version: 2.1
Name: business-rules-reloaded
Version: 2.0.1
Summary: Python DSL for setting up business intelligence rules that can be configured without code. Based on venmo/business-rules.
Home-page: https://github.com/RonquilloAeon/business-rules
Author: RonquilloAeon
Author-email: 23411718+RonquilloAeon@users.noreply.github.com
License: MIT
Platform: UNKNOWN
Requires-Python: >=3.7,<4
License-File: LICENSE
